cic/__init__.py
cic/cmd/__init__.py
cic/cmd/export.py
cic/cmd/ext.py
cic/cmd/init.py
cic/cmd/show.py
cic/cmd/wizard.py
cic/config.py
cic/configs/docker/config.ini
cic/configs/local/config.ini
cic/configs/mainnet/config.ini
cic/configs/testnet/config.ini
cic/contract/__init__.py
cic/contract/base.py
cic/contract/components/__init__.py
cic/contract/components/attachment.py
cic/contract/components/meta.py
cic/contract/components/proof.py
cic/contract/components/token.py
cic/contract/constants.py
cic/contract/contract.py
cic/contract/csv.py
cic/contract/helpers.py
cic/contract/network.py
cic/contract/processor.py
cic/data/config/config.ini
cic/data/meta_template_v0.json
cic/data/network_template_v0.json
cic/data/proof_template_v0.json
cic/data/token_template_v0.json
cic/ext/eth/__init__.py
cic/ext/eth/rpc.py
cic/ext/eth/start.py
cic/extension.py
cic/keystore.py
cic/runnable/cic_cmd.py
cic/schema/v0.json
cic/utils.py
cic/writers.py
cic_cli-0.5.5.dist-info/LICENSE
cic_cli-0.5.5.dist-info/METADATA
cic_cli-0.5.5.dist-info/WHEEL
cic_cli-0.5.5.dist-info/entry_points.txt
cic_cli-0.5.5.dist-info/RECORD
