Metadata-Version: 2.1
Name: cic-cli
Version: 0.5.5
Summary: Generic cli tooling for the CIC token network
Home-page: https://git.grassecon.net/cicnet/cic-cli
License: GPL-3.0-or-later
Keywords: dlt,blockchain,cryptocurrency
Author: Louis Holbrook
Author-email: dev@holbrook.no
Requires-Python: >=3.8,<4.0
Classifier: Development Status :: 3 - Alpha
Classifier: Environment :: Console
Classifier: Intended Audience :: Developers
Classifier: License :: OSI Approved :: GNU General Public License v3 or later (GPLv3+)
Classifier: Operating System :: OS Independent
Classifier: Programming Language :: Python :: 3
Classifier: Programming Language :: Python :: 3.8
Classifier: Programming Language :: Python :: 3.9
Classifier: Programming Language :: Python :: 3.10
Classifier: Programming Language :: Python :: 3.11
Classifier: Programming Language :: Python :: 3
Classifier: Topic :: Internet
Provides-Extra: eth
Requires-Dist: cbor2 (>=5.4.1,<5.5.0)
Requires-Dist: chainlib (>=0.1.0,<0.2.0)
Requires-Dist: chainlib-eth (>=0.1.1,<0.2.0) ; extra == "eth"
Requires-Dist: cic-contracts (>=0.1.0,<0.2.0) ; extra == "eth"
Requires-Dist: cic-eth-registry (>=0.6.9,<0.7.0) ; extra == "eth"
Requires-Dist: cic-types (>=0.2.7,<0.3.0)
Requires-Dist: confini (>=0.6.0,<0.7.0)
Requires-Dist: eth-address-index (>=0.5.0,<0.6.0) ; extra == "eth"
Requires-Dist: eth-token-index (>=0.3.0,<0.4.0) ; extra == "eth"
Requires-Dist: funga-eth (>=0.6.0,<0.7.0)
Requires-Dist: okota (>=0.4.0,<0.5.0) ; extra == "eth"
Project-URL: Repository, https://git.grassecon.net/cicnet/cic-cli
